<?xml version="1.0"?>
<!-- <!DOCTYPE Chapters SYSTEM "matroskachapters.dtd"> -->
<Chapters>
  <EditionEntry>
    <EditionUID>19134</EditionUID>
    <EditionFlagDefault>1</EditionFlagDefault>
    <EditionFlagOrdered>1</EditionFlagOrdered>
    <ChapterAtom>
      <ChapterUID>13608</ChapterUID>
      <ChapterTimeStart>00:00:0.000000000</ChapterTimeStart>
      <ChapterTimeEnd>00:00:1.000000000</ChapterTimeEnd>
      <ChapterSegmentUID format="hex">0x17 0xc0 0x78 0x47 0xcc 0x0e 0xc1 0xc1 0x02 0x48 0x11 0xe5 0xc9 0x90 0xfa 0x67</ChapterSegmentUID>
      <ChapterSegmentEditionUID>11536</ChapterSegmentEditionUID>
      <ChapterDisplay>
        <ChapterString>north-america-0</ChapterString>
        <ChapterLanguage>eng</ChapterLanguage>
      </ChapterDisplay>
    </ChapterAtom>
    <ChapterAtom>
      <ChapterUID>28717</ChapterUID>
      <ChapterTimeStart>00:00:2.000000000</ChapterTimeStart>
      <ChapterTimeEnd>00:00:3.000000000</ChapterTimeEnd>
      <ChapterSegmentUID format="hex">0x17 0xc0 0x78 0x47 0xcc 0x0e 0xc1 0xc1 0x02 0x48 0x11 0xe5 0xc9 0x90 0xfa 0x67</ChapterSegmentUID>
      <ChapterSegmentEditionUID>11536</ChapterSegmentEditionUID>
      <ChapterDisplay>
        <ChapterString>north-america-1</ChapterString>
        <ChapterLanguage>eng</ChapterLanguage>
      </ChapterDisplay>
    </ChapterAtom>
    <ChapterAtom>
      <ChapterUID>15920</ChapterUID>
      <ChapterTimeStart>00:00:4.000000000</ChapterTimeStart>
      <ChapterTimeEnd>00:00:5.000000000</ChapterTimeEnd>
      <ChapterSegmentUID format="hex">0x17 0xc0 0x78 0x47 0xcc 0x0e 0xc1 0xc1 0x02 0x48 0x11 0xe5 0xc9 0x90 0xfa 0x67</ChapterSegmentUID>
      <ChapterSegmentEditionUID>11536</ChapterSegmentEditionUID>
      <ChapterDisplay>
        <ChapterString>north-america-2</ChapterString>
        <ChapterLanguage>eng</ChapterLanguage>
      </ChapterDisplay>
    </ChapterAtom>
    <ChapterAtom>
      <ChapterUID>13316</ChapterUID>
      <ChapterTimeStart>00:00:6.000000000</ChapterTimeStart>
      <ChapterTimeEnd>00:00:7.000000000</ChapterTimeEnd>
      <ChapterSegmentUID format="hex">0x17 0xc0 0x78 0x47 0xcc 0x0e 0xc1 0xc1 0x02 0x48 0x11 0xe5 0xc9 0x90 0xfa 0x67</ChapterSegmentUID>
      <ChapterSegmentEditionUID>11536</ChapterSegmentEditionUID>
      <ChapterDisplay>
        <ChapterString>north-america-3</ChapterString>
        <ChapterLanguage>eng</ChapterLanguage>
      </ChapterDisplay>
    </ChapterAtom>
    <ChapterAtom>
      <ChapterUID>30986</ChapterUID>
      <ChapterTimeStart>00:00:8.000000000</ChapterTimeStart>
      <ChapterTimeEnd>00:00:9.000000000</ChapterTimeEnd>
      <ChapterSegmentUID format="hex">0x17 0xc0 0x78 0x47 0xcc 0x0e 0xc1 0xc1 0x02 0x48 0x11 0xe5 0xc9 0x90 0xfa 0x67</ChapterSegmentUID>
      <ChapterSegmentEditionUID>11536</ChapterSegmentEditionUID>
      <ChapterDisplay>
        <ChapterString>north-america-4</ChapterString>
        <ChapterLanguage>eng</ChapterLanguage>
      </ChapterDisplay>
    </ChapterAtom>
    <ChapterAtom>
      <ChapterUID>5724</ChapterUID>
      <ChapterTimeStart>00:00:10.000000000</ChapterTimeStart>
      <ChapterTimeEnd>00:00:11.000000000</ChapterTimeEnd>
      <ChapterSegmentUID format="hex">0x17 0xc0 0x78 0x47 0xcc 0x0e 0xc1 0xc1 0x02 0x48 0x11 0xe5 0xc9 0x90 0xfa 0x67</ChapterSegmentUID>
      <ChapterSegmentEditionUID>11536</ChapterSegmentEditionUID>
      <ChapterDisplay>
        <ChapterString>north-america-5</ChapterString>
        <ChapterLanguage>eng</ChapterLanguage>
      </ChapterDisplay>
    </ChapterAtom>
    <ChapterAtom>
      <ChapterUID>26869</ChapterUID>
      <ChapterTimeStart>00:00:0.000000000</ChapterTimeStart>
      <ChapterTimeEnd>00:00:1.000000000</ChapterTimeEnd>
      <ChapterSegmentUID format="hex">0x06 0x36 0xe1 0xa6 0xda 0x0d 0xa9 0xd9 0xbb 0x92 0x09 0x97 0xa7 0xaa 0xee 0xd5</ChapterSegmentUID>
      <ChapterSegmentEditionUID>10837</ChapterSegmentEditionUID>
      <ChapterDisplay>
        <ChapterString>europe-0</ChapterString>
        <ChapterLanguage>eng</ChapterLanguage>
      </ChapterDisplay>
    </ChapterAtom>
    <ChapterAtom>
      <ChapterUID>12875</ChapterUID>
      <ChapterTimeStart>00:00:2.000000000</ChapterTimeStart>
      <ChapterTimeEnd>00:00:3.000000000</ChapterTimeEnd>
      <ChapterSegmentUID format="hex">0x06 0x36 0xe1 0xa6 0xda 0x0d 0xa9 0xd9 0xbb 0x92 0x09 0x97 0xa7 0xaa 0xee 0xd5</ChapterSegmentUID>
      <ChapterSegmentEditionUID>10837</ChapterSegmentEditionUID>
      <ChapterDisplay>
        <ChapterString>europe-1</ChapterString>
        <ChapterLanguage>eng</ChapterLanguage>
      </ChapterDisplay>
    </ChapterAtom>
    <ChapterAtom>
      <ChapterUID>8717</ChapterUID>
      <ChapterTimeStart>00:00:4.000000000</ChapterTimeStart>
      <ChapterTimeEnd>00:00:5.000000000</ChapterTimeEnd>
      <ChapterSegmentUID format="hex">0x06 0x36 0xe1 0xa6 0xda 0x0d 0xa9 0xd9 0xbb 0x92 0x09 0x97 0xa7 0xaa 0xee 0xd5</ChapterSegmentUID>
      <ChapterSegmentEditionUID>10837</ChapterSegmentEditionUID>
      <ChapterDisplay>
        <ChapterString>europe-2</ChapterString>
        <ChapterLanguage>eng</ChapterLanguage>
      </ChapterDisplay>
    </ChapterAtom>
    <ChapterAtom>
      <ChapterUID>12498</ChapterUID>
      <ChapterTimeStart>00:00:6.000000000</ChapterTimeStart>
      <ChapterTimeEnd>00:00:7.000000000</ChapterTimeEnd>
      <ChapterSegmentUID format="hex">0x06 0x36 0xe1 0xa6 0xda 0x0d 0xa9 0xd9 0xbb 0x92 0x09 0x97 0xa7 0xaa 0xee 0xd5</ChapterSegmentUID>
      <ChapterSegmentEditionUID>10837</ChapterSegmentEditionUID>
      <ChapterDisplay>
        <ChapterString>europe-3</ChapterString>
        <ChapterLanguage>eng</ChapterLanguage>
      </ChapterDisplay>
    </ChapterAtom>
    <ChapterAtom>
      <ChapterUID>10827</ChapterUID>
      <ChapterTimeStart>00:00:8.000000000</ChapterTimeStart>
      <ChapterTimeEnd>00:00:9.000000000</ChapterTimeEnd>
      <ChapterSegmentUID format="hex">0x06 0x36 0xe1 0xa6 0xda 0x0d 0xa9 0xd9 0xbb 0x92 0x09 0x97 0xa7 0xaa 0xee 0xd5</ChapterSegmentUID>
      <ChapterSegmentEditionUID>10837</ChapterSegmentEditionUID>
      <ChapterDisplay>
        <ChapterString>europe-4</ChapterString>
        <ChapterLanguage>eng</ChapterLanguage>
      </ChapterDisplay>
    </ChapterAtom>
    <ChapterAtom>
      <ChapterUID>23524</ChapterUID>
      <ChapterTimeStart>00:00:10.000000000</ChapterTimeStart>
      <ChapterTimeEnd>00:00:11.000000000</ChapterTimeEnd>
      <ChapterSegmentUID format="hex">0x06 0x36 0xe1 0xa6 0xda 0x0d 0xa9 0xd9 0xbb 0x92 0x09 0x97 0xa7 0xaa 0xee 0xd5</ChapterSegmentUID>
      <ChapterSegmentEditionUID>10837</ChapterSegmentEditionUID>
      <ChapterDisplay>
        <ChapterString>europe-5</ChapterString>
        <ChapterLanguage>eng</ChapterLanguage>
      </ChapterDisplay>
    </ChapterAtom>
    <ChapterAtom>
      <ChapterUID>12114</ChapterUID>
      <ChapterTimeStart>00:00:0.000000000</ChapterTimeStart>
      <ChapterTimeEnd>00:00:1.000000000</ChapterTimeEnd>
      <ChapterSegmentUID format="hex">0x5c 0x00 0xaf 0xd3 0xc4 0x4a 0x83 0xcb 0xf9 0x93 0xa2 0x05 0xe8 0x6b 0x9b 0x69</ChapterSegmentUID>
      <ChapterSegmentEditionUID>29510</ChapterSegmentEditionUID>
      <ChapterDisplay>
        <ChapterString>asia-0</ChapterString>
        <ChapterLanguage>eng</ChapterLanguage>
      </ChapterDisplay>
    </ChapterAtom>
    <ChapterAtom>
      <ChapterUID>5472</ChapterUID>
      <ChapterTimeStart>00:00:2.000000000</ChapterTimeStart>
      <ChapterTimeEnd>00:00:3.000000000</ChapterTimeEnd>
      <ChapterSegmentUID format="hex">0x5c 0x00 0xaf 0xd3 0xc4 0x4a 0x83 0xcb 0xf9 0x93 0xa2 0x05 0xe8 0x6b 0x9b 0x69</ChapterSegmentUID>
      <ChapterSegmentEditionUID>29510</ChapterSegmentEditionUID>
      <ChapterDisplay>
        <ChapterString>asia-1</ChapterString>
        <ChapterLanguage>eng</ChapterLanguage>
      </ChapterDisplay>
    </ChapterAtom>
    <ChapterAtom>
      <ChapterUID>2832</ChapterUID>
      <ChapterTimeStart>00:00:4.000000000</ChapterTimeStart>
      <ChapterTimeEnd>00:00:5.000000000</ChapterTimeEnd>
      <ChapterSegmentUID format="hex">0x5c 0x00 0xaf 0xd3 0xc4 0x4a 0x83 0xcb 0xf9 0x93 0xa2 0x05 0xe8 0x6b 0x9b 0x69</ChapterSegmentUID>
      <ChapterSegmentEditionUID>29510</ChapterSegmentEditionUID>
      <ChapterDisplay>
        <ChapterString>asia-2</ChapterString>
        <ChapterLanguage>eng</ChapterLanguage>
      </ChapterDisplay>
    </ChapterAtom>
    <ChapterAtom>
      <ChapterUID>4543</ChapterUID>
      <ChapterTimeStart>00:00:6.000000000</ChapterTimeStart>
      <ChapterTimeEnd>00:00:7.000000000</ChapterTimeEnd>
      <ChapterSegmentUID format="hex">0x5c 0x00 0xaf 0xd3 0xc4 0x4a 0x83 0xcb 0xf9 0x93 0xa2 0x05 0xe8 0x6b 0x9b 0x69</ChapterSegmentUID>
      <ChapterSegmentEditionUID>29510</ChapterSegmentEditionUID>
      <ChapterDisplay>
        <ChapterString>asia-3</ChapterString>
        <ChapterLanguage>eng</ChapterLanguage>
      </ChapterDisplay>
    </ChapterAtom>
  </EditionEntry>
</Chapters>
